spiral/__about__.py
spiral/__init__.py
spiral/core/__init__.py
spiral/core/template.py
spiral/core/utils.py
spiral/core/agents/random.py
spiral/core/agents/utils.py
spiral/core/envs/__init__.py
spiral/core/envs/KuhnPoker/env.py
spiral/core/envs/LiarsDice/env.py
spiral/core/envs/PigDice/env.py
spiral/core/envs/SimpleBlindAuction/env.py
spiral/core/envs/SimpleNegotiation/env.py
spiral/core/envs/SimpleNegotiation/five_resource_env.py
spiral/core/envs/SpellingBee/env.py
spiral/core/envs/TruthAndDeception/env.py
spiral/core/envs/WordChains/env.py
spiral/core/envs/test/test_simple_negotiation.py
spiral/oat/__init__.py
spiral/oat/components.py
spiral/oat/metrics.py
spiral/tinker/__init__.py
spiral/tinker/dataset.py
spiral/tinker/renderer.py
spiral/tinker/utils.py
spiral/tinker/async_actor_learner/__init__.py
spiral/tinker/async_actor_learner/actor.py
spiral/tinker/async_actor_learner/learner.py
spiral/tinker/async_actor_learner/replay_buffer.py
spiral/tinker/eval/__init__.py
spiral/tinker/eval/evaluator.py
spiral/tinker/eval/math_test.py
spiral/tinker/training/__init__.py
spiral/tinker/training/env.py
spiral/tinker/training/population.py
spiral/tinker/training/rollouts.py
spiral/tinker/training/train.py
spiral/tinker/training/train_step.py
spiral_rl-0.2.0.dist-info/METADATA
spiral_rl-0.2.0.dist-info/WHEEL
spiral_rl-0.2.0.dist-info/entry_points.txt
spiral_rl-0.2.0.dist-info/licenses/LICENSE
spiral_rl-0.2.0.dist-info/RECORD
