Metadata-Version: 2.4
Name: spiral-rl
Version: 0.2.0
Summary: SPIRAL: Self-Play Reinforcement Learning framework for training LLMs on competitive games
Project-URL: Homepage, https://github.com/spiral-rl/spiral-on-tinker
Project-URL: Documentation, https://github.com/spiral-rl/spiral-on-tinker#readme
Project-URL: Issues, https://github.com/spiral-rl/spiral-on-tinker/issues
Project-URL: Source, https://github.com/spiral-rl/spiral-on-tinker
Project-URL: Repository, https://github.com/spiral-rl/spiral-on-tinker
Author-email: Bo Liu <benjaminliu.eecs@gmail.com>, Zichen Liu <lkevinzc@gmail.com>, Simon Yu <simon011130@gmail.com>
Maintainer-email: SPIRAL Team <benjaminliu.eecs@gmail.com>
License: Apache-2.0
License-File: LICENSE
Keywords: game-playing,language-models,llm,multi-agent,reinforcement-learning,self-play
Classifier: Development Status :: 3 - Alpha
Classifier: Intended Audience :: Science/Research
Classifier: License :: OSI Approved :: Apache Software License
Classifier: Programming Language :: Python :: 3
Classifier: Programming Language :: Python :: 3.10
Classifier: Topic :: Scientific/Engineering :: Artificial Intelligence
Requires-Python: >=3.10
Requires-Dist: antlr4-python3-runtime==4.13.2
Requires-Dist: human-eval
Requires-Dist: latex2sympy2
Requires-Dist: numpy>=1.24.0
Requires-Dist: tabulate
Requires-Dist: textarena==0.6.4
Requires-Dist: textblob
Requires-Dist: tqdm>=4.65.0
Requires-Dist: weave
Provides-Extra: all
Requires-Dist: chz; extra == 'all'
Requires-Dist: oat-llm==0.2.1; extra == 'all'
Requires-Dist: tinker; extra == 'all'
Requires-Dist: tinker-cookbook; extra == 'all'
Requires-Dist: vllm==0.8.4; extra == 'all'
Provides-Extra: dev
Requires-Dist: black>=23.0.0; extra == 'dev'
Requires-Dist: isort>=5.12.0; extra == 'dev'
Requires-Dist: mypy>=1.0.0; extra == 'dev'
Requires-Dist: pylint>=2.17.0; extra == 'dev'
Requires-Dist: pytest>=7.0.0; extra == 'dev'
Provides-Extra: full
Requires-Dist: black>=23.0.0; extra == 'full'
Requires-Dist: chz; extra == 'full'
Requires-Dist: isort>=5.12.0; extra == 'full'
Requires-Dist: mypy>=1.0.0; extra == 'full'
Requires-Dist: oat-llm==0.2.1; extra == 'full'
Requires-Dist: pylint>=2.17.0; extra == 'full'
Requires-Dist: pytest>=7.0.0; extra == 'full'
Requires-Dist: tinker; extra == 'full'
Requires-Dist: tinker-cookbook; extra == 'full'
Requires-Dist: vllm==0.8.4; extra == 'full'
Requires-Dist: wandb>=0.15.0; extra == 'full'
Provides-Extra: oat
Requires-Dist: oat-llm==0.2.1; extra == 'oat'
Requires-Dist: vllm==0.8.4; extra == 'oat'
Provides-Extra: tinker
Requires-Dist: chz; extra == 'tinker'
Requires-Dist: tinker; extra == 'tinker'
Requires-Dist: tinker-cookbook; extra == 'tinker'
